AUTHORS
COPYING
MANIFEST.in
README.creole
setup.py
loghacks/__init__.py
loghacks/handlers.py
loghacks.egg-info/PKG-INFO
loghacks.egg-info/SOURCES.txt
loghacks.egg-info/dependency_links.txt
loghacks.egg-info/top_level.txt