Metadata-Version: 1.0
Name: loghacks
Version: 0.05
Summary: python logging utility for django projects
Home-page: http://github.com/woome/loghacks
Author: Otu Ekanem
Author-email: io2@woome.com
License: GNU GPL v3
Download-URL: http://github.com/woome/loghacks/tarball/master
Platform: any
Classifier: Development Status :: 3 - Alpha
Classifier: Intended Audience :: Developers
Classifier: License :: OSI Approved :: GNU General Public License (GPL)
Classifier: Operating System :: OS Independent
Classifier: Programming Language :: Python
Classifier: Topic :: Utilities
